slime_mind/.DS_Store
slime_mind/__init__.py
slime_mind/main.py
slime_mind/.vscode/launch.json
slime_mind/engine/engine.py
slime_mind/engine/game_recorder.py
slime_mind/engine/map.py
slime_mind/engine/plant.py
slime_mind/engine/rock.py
slime_mind/engine/slime.py
slime_mind/engine/sprite_man.py
slime_mind/images/Background.png
slime_mind/images/plant_1.png
slime_mind/images/plant_2.png
slime_mind/images/red_1.png
slime_mind/images/rock_1.png
slime_mind/images/slime_default_1.png
slime_mind/images/slime_default_2.png
slime_mind/images/slime_default_king_1.png
slime_mind/images/slime_default_king_2.png
slime_mind/images/slime_purple_1.png
slime_mind/images/slime_purple_king_2.png
slime_mind/images/Red/Red_1.pdn
slime_mind/images/Red/red_1.png
slime_mind/models/commands.py
slime_mind/models/player_base.py
slime_mind/resources/config.ini
slime_mind/runners/multi_match.py
slime_mind/runners/replay.py
slime_mind/runners/runner_base.py
slime_mind/runners/single_match.py
slime_mind/timer/convert_timings.py
slime_mind/timer/timer.py
slime_mind/visualizer/plant_sprite.py
slime_mind/visualizer/rock_sprite.py
slime_mind/visualizer/slime_sprite.py
slime_mind/visualizer/visualizer.py
slime_mind-2.0.0.dist-info/LICENSE
slime_mind-2.0.0.dist-info/METADATA
slime_mind-2.0.0.dist-info/WHEEL
slime_mind-2.0.0.dist-info/top_level.txt
slime_mind-2.0.0.dist-info/RECORD
