Metadata-Version: 2.1
Name: slime-mind
Version: 2.0.0
Summary: AI competition game
Home-page: https://github.com/teofrastusb/SlimeMind
Author: Alex Havermann, Ian Kottman
License: UNKNOWN
Platform: UNKNOWN
Classifier: Programming Language :: Python :: 3
Classifier: License :: OSI Approved :: MIT License
Classifier: Operating System :: OS Independent
Requires-Dist: arcade
